{"distance": 1.4142135623730951, "nb_steps": 2, "matrix": [[{"color": "a", "xdirs": [], "ydirs": []}, {"color": "a", "xdirs": [1], "ydirs": [1]}, {"color": "e", "xdirs": [1, -1], "ydirs": []}, {"color": "w", "xdirs": [-1], "ydirs": [1]}, {"color": "a", "xdirs": [], "ydirs": []}], [{"color": "w", "xdirs": [], "ydirs": [1]}, {"color": "f", "xdirs": [1], "ydirs": [-1]}, {"color": "f", "xdirs": [-1], "ydirs": [1]}, {"color": "f", "xdirs": [], "ydirs": [-1]}, {"color": "a", "xdirs": [], "ydirs": [1]}], [{"color": "e", "xdirs": [1], "ydirs": [-1]}, {"color": "a", "xdirs": [-1], "ydirs": [1]}, {"color": "w", "xdirs": [1], "ydirs": [1, -1]}, {"color": "f", "xdirs": [1, -1], "ydirs": [1]}, {"color": "w", "xdirs": [-1], "ydirs": [-1]}], [{"color": "f", "xdirs": [1], "ydirs": []}, {"color": "f", "xdirs": [1, -1], "ydirs": [-1]}, {"color": "e", "xdirs": [1, -1], "ydirs": [-1]}, {"color": "a", "xdirs": [1, -1], "ydirs": [-1]}, {"color": "a", "xdirs": [-1], "ydirs": [1]}], [{"color": "e", "xdirs": [], "ydirs": []}, {"color": "f", "xdirs": [-1], "ydirs": []}, {"color": "e", "xdirs": [1], "ydirs": []}, {"color": "w", "xdirs": [1, -1], "ydirs": []}, {"color": "f", "xdirs": [-1], "ydirs": [-1]}]], "fireman_position": {"y": 2, "x": 3}, "fitness": 0.18866666666666665, "solved": true, "score": 1.4142135623730951, "steps": 0, "compactness": 0.3599999999999999, "waterman_position": {"y": 2, "x": 2}, "earthman_position": {"y": 2, "x": 0}, "airman_position": {"y": 3, "x": 3}, "chest_position": {"y": 1, "x": 1}}